dhubse/VERSION
dhubse/__init__.py
dhubse/dhubse.py
dhubse/utils/__init__.py
dhubse/utils/cli_args.py
dhubse/utils/docker_registry_api.py
dhubse/utils/meta_v.py
dhubse/utils/tool_box.py
dhubse-0.0.1.dist-info/LICENSE
dhubse-0.0.1.dist-info/METADATA
dhubse-0.0.1.dist-info/WHEEL
dhubse-0.0.1.dist-info/entry_points.txt
dhubse-0.0.1.dist-info/top_level.txt
dhubse-0.0.1.dist-info/RECORD
