Metadata-Version: 2.1
Name: dhubse
Version: 0.0.1
Summary: Docker image search tool.
Home-page: https://github.com/unihon/dhubse
Author: unihon
Author-email: unihon@outlook.com
License: LGPLv3
Project-URL: Bug Reports, https://github.com/unihon/dhubse/issues
Project-URL: Funding, https://pypi.org/project/dhubse/
Project-URL: Source, https://github.com/unihon/dhubse
Keywords: docker image tag search registry
Platform: UNKNOWN
Classifier: Programming Language :: Python :: 3
Classifier: License :: OSI Approved :: GNU Lesser General Public License v3 (LGPLv3)
Requires-Python: >=3.5
Requires-Dist: requests
Requires-Dist: tabulate
